{"nodes": [{"id": "c_users_asus_projects_emtools_lib_domain_entities_paste_dart", "label": "paste.dart", "file_type": "code", "source_file": "lib/domain/entities/paste.dart", "source_location": null}, {"id": "entities_paste_paste", "label": "Paste", "file_type": "code", "source_file": "lib/domain/entities/paste.dart", "source_location": null}, {"id": "entities_paste_pastecreate", "label": "PasteCreate", "file_type": "code", "source_file": "lib/domain/entities/paste.dart", "source_location": null}, {"id": "entities_paste_id", "label": "id", "file_type": "code", "source_file": "lib/domain/entities/paste.dart", "source_location": null}, {"id": "entities_paste_title", "label": "title", "file_type": "code", "source_file": "lib/domain/entities/paste.dart", "source_location": null}, {"id": "string", "label": "String?", "file_type": "code", "source_file": null, "source_location": null}, {"id": "entities_paste_content", "label": "content", "file_type": "code", "source_file": "lib/domain/entities/paste.dart", "source_location": null}, {"id": "entities_paste_language", "label": "language", "file_type": "code", "source_file": "lib/domain/entities/paste.dart", "source_location": null}, {"id": "entities_paste_isprotected", "label": "isProtected", "file_type": "code", "source_file": "lib/domain/entities/paste.dart", "source_location": null}, {"id": "entities_paste_expiresat", "label": "expiresAt", "file_type": "code", "source_file": "lib/domain/entities/paste.dart", "source_location": null}, {"id": "datetime", "label": "DateTime", "file_type": "code", "source_file": null, "source_location": null}, {"id": "entities_paste_burnafterread", "label": "burnAfterRead", "file_type": "code", "source_file": "lib/domain/entities/paste.dart", "source_location": null}, {"id": "entities_paste_views", "label": "views", "file_type": "code", "source_file": "lib/domain/entities/paste.dart", "source_location": null}, {"id": "entities_paste_maxviews", "label": "maxViews", "file_type": "code", "source_file": "lib/domain/entities/paste.dart", "source_location": null}, {"id": "int", "label": "int?", "file_type": "code", "source_file": null, "source_location": null}, {"id": "entities_paste_images", "label": "images", "file_type": "code", "source_file": "lib/domain/entities/paste.dart", "source_location": null}, {"id": "list", "label": "List", "file_type": "code", "source_file": null, "source_location": null}, {"id": "entities_paste_password", "label": "password", "file_type": "code", "source_file": "lib/domain/entities/paste.dart", "source_location": null}, {"id": "entities_paste_expiresinhours", "label": "expiresInHours", "file_type": "code", "source_file": "lib/domain/entities/paste.dart", "source_location": null}, {"id": "entities_paste_fromjson", "label": "fromJson", "file_type": "code", "source_file": "lib/domain/entities/paste.dart", "source_location": null}, {"id": "entities_paste_tojson", "label": "toJson", "file_type": "code", "source_file": "lib/domain/entities/paste.dart", "source_location": null}], "edges": [{"source": "c_users_asus_projects_emtools_lib_domain_entities_paste_dart", "target": "entities_paste_paste", "relation": "defines", "confidence": "EXTRACTED", "confidence_score": 1.0, "source_file": "lib/domain/entities/paste.dart", "source_location": null, "weight": 1.0}, {"source": "c_users_asus_projects_emtools_lib_domain_entities_paste_dart", "target": "entities_paste_pastecreate", "relation": "defines", "confidence": "EXTRACTED", "confidence_score": 1.0, "source_file": "lib/domain/entities/paste.dart", "source_location": null, "weight": 1.0}, {"source": "c_users_asus_projects_emtools_lib_domain_entities_paste_dart", "target": "entities_paste_id", "relation": "defines", "confidence": "EXTRACTED", "confidence_score": 1.0, "source_file": "lib/domain/entities/paste.dart", "source_location": null, "weight": 1.0}, {"source": "c_users_asus_projects_emtools_lib_domain_entities_paste_dart", "target": "entities_paste_title", "relation": "defines", "confidence": "EXTRACTED", "confidence_score": 1.0, "source_file": "lib/domain/entities/paste.dart", "source_location": null, "weight": 1.0}, {"source": "c_users_asus_projects_emtools_lib_domain_entities_paste_dart", "target": "string", "relation": "references", "confidence": "EXTRACTED", "confidence_score": 1.0, "source_file": "lib/domain/entities/paste.dart", "source_location": null, "weight": 1.0, "context": "variable_type"}, {"source": "c_users_asus_projects_emtools_lib_domain_entities_paste_dart", "target": "entities_paste_content", "relation": "defines", "confidence": "EXTRACTED", "confidence_score": 1.0, "source_file": "lib/domain/entities/paste.dart", "source_location": null, "weight": 1.0}, {"source": "c_users_asus_projects_emtools_lib_domain_entities_paste_dart", "target": "entities_paste_language", "relation": "defines", "confidence": "EXTRACTED", "confidence_score": 1.0, "source_file": "lib/domain/entities/paste.dart", "source_location": null, "weight": 1.0}, {"source": "c_users_asus_projects_emtools_lib_domain_entities_paste_dart", "target": "entities_paste_isprotected", "relation": "defines", "confidence": "EXTRACTED", "confidence_score": 1.0, "source_file": "lib/domain/entities/paste.dart", "source_location": null, "weight": 1.0}, {"source": "c_users_asus_projects_emtools_lib_domain_entities_paste_dart", "target": "entities_paste_expiresat", "relation": "defines", "confidence": "EXTRACTED", "confidence_score": 1.0, "source_file": "lib/domain/entities/paste.dart", "source_location": null, "weight": 1.0}, {"source": "c_users_asus_projects_emtools_lib_domain_entities_paste_dart", "target": "datetime", "relation": "references", "confidence": "EXTRACTED", "confidence_score": 1.0, "source_file": "lib/domain/entities/paste.dart", "source_location": null, "weight": 1.0, "context": "variable_type"}, {"source": "c_users_asus_projects_emtools_lib_domain_entities_paste_dart", "target": "entities_paste_burnafterread", "relation": "defines", "confidence": "EXTRACTED", "confidence_score": 1.0, "source_file": "lib/domain/entities/paste.dart", "source_location": null, "weight": 1.0}, {"source": "c_users_asus_projects_emtools_lib_domain_entities_paste_dart", "target": "entities_paste_views", "relation": "defines", "confidence": "EXTRACTED", "confidence_score": 1.0, "source_file": "lib/domain/entities/paste.dart", "source_location": null, "weight": 1.0}, {"source": "c_users_asus_projects_emtools_lib_domain_entities_paste_dart", "target": "entities_paste_maxviews", "relation": "defines", "confidence": "EXTRACTED", "confidence_score": 1.0, "source_file": "lib/domain/entities/paste.dart", "source_location": null, "weight": 1.0}, {"source": "c_users_asus_projects_emtools_lib_domain_entities_paste_dart", "target": "int", "relation": "references", "confidence": "EXTRACTED", "confidence_score": 1.0, "source_file": "lib/domain/entities/paste.dart", "source_location": null, "weight": 1.0, "context": "variable_type"}, {"source": "c_users_asus_projects_emtools_lib_domain_entities_paste_dart", "target": "entities_paste_images", "relation": "defines", "confidence": "EXTRACTED", "confidence_score": 1.0, "source_file": "lib/domain/entities/paste.dart", "source_location": null, "weight": 1.0}, {"source": "c_users_asus_projects_emtools_lib_domain_entities_paste_dart", "target": "list", "relation": "references", "confidence": "EXTRACTED", "confidence_score": 1.0, "source_file": "lib/domain/entities/paste.dart", "source_location": null, "weight": 1.0, "context": "variable_type"}, {"source": "c_users_asus_projects_emtools_lib_domain_entities_paste_dart", "target": "entities_paste_content", "relation": "defines", "confidence": "EXTRACTED", "confidence_score": 1.0, "source_file": "lib/domain/entities/paste.dart", "source_location": null, "weight": 1.0}, {"source": "c_users_asus_projects_emtools_lib_domain_entities_paste_dart", "target": "entities_paste_title", "relation": "defines", "confidence": "EXTRACTED", "confidence_score": 1.0, "source_file": "lib/domain/entities/paste.dart", "source_location": null, "weight": 1.0}, {"source": "c_users_asus_projects_emtools_lib_domain_entities_paste_dart", "target": "string", "relation": "references", "confidence": "EXTRACTED", "confidence_score": 1.0, "source_file": "lib/domain/entities/paste.dart", "source_location": null, "weight": 1.0, "context": "variable_type"}, {"source": "c_users_asus_projects_emtools_lib_domain_entities_paste_dart", "target": "entities_paste_language", "relation": "defines", "confidence": "EXTRACTED", "confidence_score": 1.0, "source_file": "lib/domain/entities/paste.dart", "source_location": null, "weight": 1.0}, {"source": "c_users_asus_projects_emtools_lib_domain_entities_paste_dart", "target": "entities_paste_password", "relation": "defines", "confidence": "EXTRACTED", "confidence_score": 1.0, "source_file": "lib/domain/entities/paste.dart", "source_location": null, "weight": 1.0}, {"source": "c_users_asus_projects_emtools_lib_domain_entities_paste_dart", "target": "string", "relation": "references", "confidence": "EXTRACTED", "confidence_score": 1.0, "source_file": "lib/domain/entities/paste.dart", "source_location": null, "weight": 1.0, "context": "variable_type"}, {"source": "c_users_asus_projects_emtools_lib_domain_entities_paste_dart", "target": "entities_paste_expiresinhours", "relation": "defines", "confidence": "EXTRACTED", "confidence_score": 1.0, "source_file": "lib/domain/entities/paste.dart", "source_location": null, "weight": 1.0}, {"source": "c_users_asus_projects_emtools_lib_domain_entities_paste_dart", "target": "entities_paste_burnafterread", "relation": "defines", "confidence": "EXTRACTED", "confidence_score": 1.0, "source_file": "lib/domain/entities/paste.dart", "source_location": null, "weight": 1.0}, {"source": "c_users_asus_projects_emtools_lib_domain_entities_paste_dart", "target": "entities_paste_maxviews", "relation": "defines", "confidence": "EXTRACTED", "confidence_score": 1.0, "source_file": "lib/domain/entities/paste.dart", "source_location": null, "weight": 1.0}, {"source": "c_users_asus_projects_emtools_lib_domain_entities_paste_dart", "target": "int", "relation": "references", "confidence": "EXTRACTED", "confidence_score": 1.0, "source_file": "lib/domain/entities/paste.dart", "source_location": null, "weight": 1.0, "context": "variable_type"}, {"source": "c_users_asus_projects_emtools_lib_domain_entities_paste_dart", "target": "entities_paste_images", "relation": "defines", "confidence": "EXTRACTED", "confidence_score": 1.0, "source_file": "lib/domain/entities/paste.dart", "source_location": null, "weight": 1.0}, {"source": "c_users_asus_projects_emtools_lib_domain_entities_paste_dart", "target": "list", "relation": "references", "confidence": "EXTRACTED", "confidence_score": 1.0, "source_file": "lib/domain/entities/paste.dart", "source_location": null, "weight": 1.0, "context": "variable_type"}, {"source": "c_users_asus_projects_emtools_lib_domain_entities_paste_dart", "target": "entities_paste_fromjson", "relation": "defines", "confidence": "EXTRACTED", "confidence_score": 1.0, "source_file": "lib/domain/entities/paste.dart", "source_location": null, "weight": 1.0}, {"source": "c_users_asus_projects_emtools_lib_domain_entities_paste_dart", "target": "entities_paste_tojson", "relation": "defines", "confidence": "EXTRACTED", "confidence_score": 1.0, "source_file": "lib/domain/entities/paste.dart", "source_location": null, "weight": 1.0}]}